Workbook

Sheet 利益計算
A1: WINDY 1枚あたりの利益計算
A2: 黄色のマスだけ入力してください。緑は自動計算。灰色は公式ページで確認した手数料（変わったら書き換える）。
A4: 項目 | B4: 半袖T | C4: ロンT | D4: 説明
A5: 【入力】販売価格（税込） | D5: BASEで表示する値段
A6: 【入力】お客さんから受け取る送料 | D6: 送料無料にするなら 0 を入れる
A7: 【入力】Printful 商品代（ボディ＋印刷） | D7: Printfulの商品ページ・注文画面に出る金額。ドル表示ならドルのまま入れる
A8: 【入力】Printful 送料（日本向け1枚目） | D8: 注文画面で確認した金額。2枚以上まとめて買われると1枚あたりは下がる
A9: 【入力】Printful 請求に上乗せされる税など（%） | D9: 未確認。消費税などが上乗せされるか、最初の注文の請求書で確認して入れる（無ければ0）
A10: 【入力】為替レート（1ドル＝何円） | D10: 上の7・8行がドルなら入れる。円で入れた場合は 1 を入れる
A12: BASE 決済手数料（率） | B12: 0.036 | C12: 0.036 | D12: BASE公式 料金ページ（スタンダードプラン）で確認 2026-10-23
A13: BASE 決済手数料（1注文ごとの固定額） | B13: 40 | C13: 40 | D13: 同上
A14: BASE サービス利用料（率） | B14: 0.03 | C14: 0.03 | D14: 同上
A15: 振込1回で引かれる手数料の合計 | B15: 750 | C15: 750 | D15: BASE公式ヘルプ: 振込手数料250円＋事務手数料500円(振込額2万円未満のとき。2万円以上は0円→250を入れる)
A16: 【入力】1回の振込で何枚分まとめて受け取るか | D16: 例: 月1回振込で10枚売れたら 10。空欄なら振込手数料は計算に入れない
A18: お客さんの支払い合計 | B18: =IF(COUNT(B5,B7,B8,B10)=4,B5+N(B6),"未入力") | C18: =IF(COUNT(C5,C7,C8,C10)=4,C5+N(C6),"未入力") | D18: 販売価格＋送料。BASEの手数料はこの合計にかかる（確信度: 中）
A19: − BASE 決済手数料 | B19: =IF(COUNT(B5,B7,B8,B10)=4,ROUND(B18*B12+B13,0),"未入力") | C19: =IF(COUNT(C5,C7,C8,C10)=4,ROUND(C18*C12+C13,0),"未入力") | D19: 合計×3.6%＋40円
A20: − BASE サービス利用料 | B20: =IF(COUNT(B5,B7,B8,B10)=4,ROUND(B18*B14,0),"未入力") | C20: =IF(COUNT(C5,C7,C8,C10)=4,ROUND(C18*C14,0),"未入力") | D20: 合計×3%
A21: − Printful への支払い（円） | B21: =IF(COUNT(B5,B7,B8,B10)=4,ROUND((B7+B8)*(1+N(B9))*B10,0),"未入力") | C21: =IF(COUNT(C5,C7,C8,C10)=4,ROUND((C7+C8)*(1+N(C9))*C10,0),"未入力") | D21: (商品代＋送料)×(1＋税)×為替
A22: − 振込手数料（1枚あたり） | B22: =IF(COUNT(B5,B7,B8,B10)=4,IF(N(B16)>0,ROUND(B15/B16,0),0),"未入力") | C22: =IF(COUNT(C5,C7,C8,C10)=4,IF(N(C16)>0,ROUND(C15/C16,0),0),"未入力") | D22: 振込1回の手数料÷まとめる枚数
A23: ＝ 1枚あたりの利益 | B23: =IF(COUNT(B5,B7,B8,B10)=4,B18-B19-B20-B21-B22,"未入力") | C23: =IF(COUNT(C5,C7,C8,C10)=4,C18-C19-C20-C21-C22,"未入力") | D23: ここがマイナスなら赤字
A24: 利益率 | B24: =IF(COUNT(B5,B7,B8,B10)=4,B23/B18,"未入力") | C24: =IF(COUNT(C5,C7,C8,C10)=4,C23/C18,"未入力") | D24: 利益÷お客さんの支払い合計
A25: 赤字にならない最低の販売価格（目安） | B25: =IF(COUNT(B5,B7,B8,B10)=4,ROUNDUP((B21+B22+B13)/(1-B12-B14)-N(B6),-1),"未入力") | C25: =IF(COUNT(C5,C7,C8,C10)=4,ROUNDUP((C21+C22+C13)/(1-C12-C14)-N(C6),-1),"未入力") | D25: これより安くすると1枚売るごとに損をする（10円単位で切り上げ）
A27: 注意
A28: ・数字を勝手に入れていません。Printfulの金額はアカウント登録後、商品を選んだ画面で確認して入れてください。
A29: ・この表に入っていない費用: サンプル代、返品・不良の対応、広告費、所得税など。
A30: ・BASEの手数料は スタンダードプラン（月額0円）の場合。グロースプラン(月額有料)だと率が変わる。
A31: ・Printfulの日本向け送料は公式の配送ページに「Tシャツ/トップス・長袖 1点目 $4.95、2点目以降 +$2.00」と表示されていた（2026-10-23、確信度: 中）。必ず注文画面の金額で入れること。

Sheet 値段ごとの比較
A1: 販売価格を変えたときの1枚あたりの利益（他の条件は「利益計算」シートの入力を使う）
A3: 販売価格（税込） | B3: 半袖Tの利益 | C3: ロンTの利益
A4: 2000 | B4: =IF(COUNT(利益計算!B7,利益計算!B8,利益計算!B10)=3,($A4+N(利益計算!B6))-ROUND(($A4+N(利益計算!B6))*利益計算!B12+利益計算!B13,0)-ROUND(($A4+N(利益計算!B6))*利益計算!B14,0)-ROUND((利益計算!B7+利益計算!B8)*(1+N(利益計算!B9))*利益計算!B10,0)-IF(N(利益計算!B16)>0,ROUND(利益計算!B15/利益計算!B16,0),0),"未入力") | C4: =IF(COUNT(利益計算!C7,利益計算!C8,利益計算!C10)=3,($A4+N(利益計算!C6))-ROUND(($A4+N(利益計算!C6))*利益計算!C12+利益計算!C13,0)-ROUND(($A4+N(利益計算!C6))*利益計算!C14,0)-ROUND((利益計算!C7+利益計算!C8)*(1+N(利益計算!C9))*利益計算!C10,0)-IF(N(利益計算!C16)>0,ROUND(利益計算!C15/利益計算!C16,0),0),"未入力")
A5: 2500 | B5: =IF(COUNT(利益計算!B7,利益計算!B8,利益計算!B10)=3,($A5+N(利益計算!B6))-ROUND(($A5+N(利益計算!B6))*利益計算!B12+利益計算!B13,0)-ROUND(($A5+N(利益計算!B6))*利益計算!B14,0)-ROUND((利益計算!B7+利益計算!B8)*(1+N(利益計算!B9))*利益計算!B10,0)-IF(N(利益計算!B16)>0,ROUND(利益計算!B15/利益計算!B16,0),0),"未入力") | C5: =IF(COUNT(利益計算!C7,利益計算!C8,利益計算!C10)=3,($A5+N(利益計算!C6))-ROUND(($A5+N(利益計算!C6))*利益計算!C12+利益計算!C13,0)-ROUND(($A5+N(利益計算!C6))*利益計算!C14,0)-ROUND((利益計算!C7+利益計算!C8)*(1+N(利益計算!C9))*利益計算!C10,0)-IF(N(利益計算!C16)>0,ROUND(利益計算!C15/利益計算!C16,0),0),"未入力")
A6: 3000 | B6: =IF(COUNT(利益計算!B7,利益計算!B8,利益計算!B10)=3,($A6+N(利益計算!B6))-ROUND(($A6+N(利益計算!B6))*利益計算!B12+利益計算!B13,0)-ROUND(($A6+N(利益計算!B6))*利益計算!B14,0)-ROUND((利益計算!B7+利益計算!B8)*(1+N(利益計算!B9))*利益計算!B10,0)-IF(N(利益計算!B16)>0,ROUND(利益計算!B15/利益計算!B16,0),0),"未入力") | C6: =IF(COUNT(利益計算!C7,利益計算!C8,利益計算!C10)=3,($A6+N(利益計算!C6))-ROUND(($A6+N(利益計算!C6))*利益計算!C12+利益計算!C13,0)-ROUND(($A6+N(利益計算!C6))*利益計算!C14,0)-ROUND((利益計算!C7+利益計算!C8)*(1+N(利益計算!C9))*利益計算!C10,0)-IF(N(利益計算!C16)>0,ROUND(利益計算!C15/利益計算!C16,0),0),"未入力")
A7: 3500 | B7: =IF(COUNT(利益計算!B7,利益計算!B8,利益計算!B10)=3,($A7+N(利益計算!B6))-ROUND(($A7+N(利益計算!B6))*利益計算!B12+利益計算!B13,0)-ROUND(($A7+N(利益計算!B6))*利益計算!B14,0)-ROUND((利益計算!B7+利益計算!B8)*(1+N(利益計算!B9))*利益計算!B10,0)-IF(N(利益計算!B16)>0,ROUND(利益計算!B15/利益計算!B16,0),0),"未入力") | C7: =IF(COUNT(利益計算!C7,利益計算!C8,利益計算!C10)=3,($A7+N(利益計算!C6))-ROUND(($A7+N(利益計算!C6))*利益計算!C12+利益計算!C13,0)-ROUND(($A7+N(利益計算!C6))*利益計算!C14,0)-ROUND((利益計算!C7+利益計算!C8)*(1+N(利益計算!C9))*利益計算!C10,0)-IF(N(利益計算!C16)>0,ROUND(利益計算!C15/利益計算!C16,0),0),"未入力")
A8: 4000 | B8: =IF(COUNT(利益計算!B7,利益計算!B8,利益計算!B10)=3,($A8+N(利益計算!B6))-ROUND(($A8+N(利益計算!B6))*利益計算!B12+利益計算!B13,0)-ROUND(($A8+N(利益計算!B6))*利益計算!B14,0)-ROUND((利益計算!B7+利益計算!B8)*(1+N(利益計算!B9))*利益計算!B10,0)-IF(N(利益計算!B16)>0,ROUND(利益計算!B15/利益計算!B16,0),0),"未入力") | C8: =IF(COUNT(利益計算!C7,利益計算!C8,利益計算!C10)=3,($A8+N(利益計算!C6))-ROUND(($A8+N(利益計算!C6))*利益計算!C12+利益計算!C13,0)-ROUND(($A8+N(利益計算!C6))*利益計算!C14,0)-ROUND((利益計算!C7+利益計算!C8)*(1+N(利益計算!C9))*利益計算!C10,0)-IF(N(利益計算!C16)>0,ROUND(利益計算!C15/利益計算!C16,0),0),"未入力")
A9: 4500 | B9: =IF(COUNT(利益計算!B7,利益計算!B8,利益計算!B10)=3,($A9+N(利益計算!B6))-ROUND(($A9+N(利益計算!B6))*利益計算!B12+利益計算!B13,0)-ROUND(($A9+N(利益計算!B6))*利益計算!B14,0)-ROUND((利益計算!B7+利益計算!B8)*(1+N(利益計算!B9))*利益計算!B10,0)-IF(N(利益計算!B16)>0,ROUND(利益計算!B15/利益計算!B16,0),0),"未入力") | C9: =IF(COUNT(利益計算!C7,利益計算!C8,利益計算!C10)=3,($A9+N(利益計算!C6))-ROUND(($A9+N(利益計算!C6))*利益計算!C12+利益計算!C13,0)-ROUND(($A9+N(利益計算!C6))*利益計算!C14,0)-ROUND((利益計算!C7+利益計算!C8)*(1+N(利益計算!C9))*利益計算!C10,0)-IF(N(利益計算!C16)>0,ROUND(利益計算!C15/利益計算!C16,0),0),"未入力")
A10: 5000 | B10: =IF(COUNT(利益計算!B7,利益計算!B8,利益計算!B10)=3,($A10+N(利益計算!B6))-ROUND(($A10+N(利益計算!B6))*利益計算!B12+利益計算!B13,0)-ROUND(($A10+N(利益計算!B6))*利益計算!B14,0)-ROUND((利益計算!B7+利益計算!B8)*(1+N(利益計算!B9))*利益計算!B10,0)-IF(N(利益計算!B16)>0,ROUND(利益計算!B15/利益計算!B16,0),0),"未入力") | C10: =IF(COUNT(利益計算!C7,利益計算!C8,利益計算!C10)=3,($A10+N(利益計算!C6))-ROUND(($A10+N(利益計算!C6))*利益計算!C12+利益計算!C13,0)-ROUND(($A10+N(利益計算!C6))*利益計算!C14,0)-ROUND((利益計算!C7+利益計算!C8)*(1+N(利益計算!C9))*利益計算!C10,0)-IF(N(利益計算!C16)>0,ROUND(利益計算!C15/利益計算!C16,0),0),"未入力")
A11: 5500 | B11: =IF(COUNT(利益計算!B7,利益計算!B8,利益計算!B10)=3,($A11+N(利益計算!B6))-ROUND(($A11+N(利益計算!B6))*利益計算!B12+利益計算!B13,0)-ROUND(($A11+N(利益計算!B6))*利益計算!B14,0)-ROUND((利益計算!B7+利益計算!B8)*(1+N(利益計算!B9))*利益計算!B10,0)-IF(N(利益計算!B16)>0,ROUND(利益計算!B15/利益計算!B16,0),0),"未入力") | C11: =IF(COUNT(利益計算!C7,利益計算!C8,利益計算!C10)=3,($A11+N(利益計算!C6))-ROUND(($A11+N(利益計算!C6))*利益計算!C12+利益計算!C13,0)-ROUND(($A11+N(利益計算!C6))*利益計算!C14,0)-ROUND((利益計算!C7+利益計算!C8)*(1+N(利益計算!C9))*利益計算!C10,0)-IF(N(利益計算!C16)>0,ROUND(利益計算!C15/利益計算!C16,0),0),"未入力")
A12: 6000 | B12: =IF(COUNT(利益計算!B7,利益計算!B8,利益計算!B10)=3,($A12+N(利益計算!B6))-ROUND(($A12+N(利益計算!B6))*利益計算!B12+利益計算!B13,0)-ROUND(($A12+N(利益計算!B6))*利益計算!B14,0)-ROUND((利益計算!B7+利益計算!B8)*(1+N(利益計算!B9))*利益計算!B10,0)-IF(N(利益計算!B16)>0,ROUND(利益計算!B15/利益計算!B16,0),0),"未入力") | C12: =IF(COUNT(利益計算!C7,利益計算!C8,利益計算!C10)=3,($A12+N(利益計算!C6))-ROUND(($A12+N(利益計算!C6))*利益計算!C12+利益計算!C13,0)-ROUND(($A12+N(利益計算!C6))*利益計算!C14,0)-ROUND((利益計算!C7+利益計算!C8)*(1+N(利益計算!C9))*利益計算!C10,0)-IF(N(利益計算!C16)>0,ROUND(利益計算!C15/利益計算!C16,0),0),"未入力")
A13: 6500 | B13: =IF(COUNT(利益計算!B7,利益計算!B8,利益計算!B10)=3,($A13+N(利益計算!B6))-ROUND(($A13+N(利益計算!B6))*利益計算!B12+利益計算!B13,0)-ROUND(($A13+N(利益計算!B6))*利益計算!B14,0)-ROUND((利益計算!B7+利益計算!B8)*(1+N(利益計算!B9))*利益計算!B10,0)-IF(N(利益計算!B16)>0,ROUND(利益計算!B15/利益計算!B16,0),0),"未入力") | C13: =IF(COUNT(利益計算!C7,利益計算!C8,利益計算!C10)=3,($A13+N(利益計算!C6))-ROUND(($A13+N(利益計算!C6))*利益計算!C12+利益計算!C13,0)-ROUND(($A13+N(利益計算!C6))*利益計算!C14,0)-ROUND((利益計算!C7+利益計算!C8)*(1+N(利益計算!C9))*利益計算!C10,0)-IF(N(利益計算!C16)>0,ROUND(利益計算!C15/利益計算!C16,0),0),"未入力")
A14: 7000 | B14: =IF(COUNT(利益計算!B7,利益計算!B8,利益計算!B10)=3,($A14+N(利益計算!B6))-ROUND(($A14+N(利益計算!B6))*利益計算!B12+利益計算!B13,0)-ROUND(($A14+N(利益計算!B6))*利益計算!B14,0)-ROUND((利益計算!B7+利益計算!B8)*(1+N(利益計算!B9))*利益計算!B10,0)-IF(N(利益計算!B16)>0,ROUND(利益計算!B15/利益計算!B16,0),0),"未入力") | C14: =IF(COUNT(利益計算!C7,利益計算!C8,利益計算!C10)=3,($A14+N(利益計算!C6))-ROUND(($A14+N(利益計算!C6))*利益計算!C12+利益計算!C13,0)-ROUND(($A14+N(利益計算!C6))*利益計算!C14,0)-ROUND((利益計算!C7+利益計算!C8)*(1+N(利益計算!C9))*利益計算!C10,0)-IF(N(利益計算!C16)>0,ROUND(利益計算!C15/利益計算!C16,0),0),"未入力")
A15: 7500 | B15: =IF(COUNT(利益計算!B7,利益計算!B8,利益計算!B10)=3,($A15+N(利益計算!B6))-ROUND(($A15+N(利益計算!B6))*利益計算!B12+利益計算!B13,0)-ROUND(($A15+N(利益計算!B6))*利益計算!B14,0)-ROUND((利益計算!B7+利益計算!B8)*(1+N(利益計算!B9))*利益計算!B10,0)-IF(N(利益計算!B16)>0,ROUND(利益計算!B15/利益計算!B16,0),0),"未入力") | C15: =IF(COUNT(利益計算!C7,利益計算!C8,利益計算!C10)=3,($A15+N(利益計算!C6))-ROUND(($A15+N(利益計算!C6))*利益計算!C12+利益計算!C13,0)-ROUND(($A15+N(利益計算!C6))*利益計算!C14,0)-ROUND((利益計算!C7+利益計算!C8)*(1+N(利益計算!C9))*利益計算!C10,0)-IF(N(利益計算!C16)>0,ROUND(利益計算!C15/利益計算!C16,0),0),"未入力")
A16: 8000 | B16: =IF(COUNT(利益計算!B7,利益計算!B8,利益計算!B10)=3,($A16+N(利益計算!B6))-ROUND(($A16+N(利益計算!B6))*利益計算!B12+利益計算!B13,0)-ROUND(($A16+N(利益計算!B6))*利益計算!B14,0)-ROUND((利益計算!B7+利益計算!B8)*(1+N(利益計算!B9))*利益計算!B10,0)-IF(N(利益計算!B16)>0,ROUND(利益計算!B15/利益計算!B16,0),0),"未入力") | C16: =IF(COUNT(利益計算!C7,利益計算!C8,利益計算!C10)=3,($A16+N(利益計算!C6))-ROUND(($A16+N(利益計算!C6))*利益計算!C12+利益計算!C13,0)-ROUND(($A16+N(利益計算!C6))*利益計算!C14,0)-ROUND((利益計算!C7+利益計算!C8)*(1+N(利益計算!C9))*利益計算!C10,0)-IF(N(利益計算!C16)>0,ROUND(利益計算!C15/利益計算!C16,0),0),"未入力")
A18: A列の販売価格は自由に書き換えられます。

Sheet 出典
A1: 項目 | B1: 出典（2026-10-23 確認）
A2: BASE 手数料 3.6%＋40円、サービス利用料3% | B2: https://thebase.com/price/
A3: BASE 振込手数料250円・事務手数料500円(2万円未満) | B3: https://help.thebase.in/hc/ja/articles/206341302
A4: Printful×BASE 連携 手数料表記 | B4: https://www.printful.com/jp/integrations/base
A5: Printful 日本向け送料 | B5: https://www.printful.com/jp/shipping
